llama_index/indices/managed/postgresml/__init__.py
llama_index/indices/managed/postgresml/base.py
llama_index/indices/managed/postgresml/query.py
llama_index/indices/managed/postgresml/retriever.py
llama_index_indices_managed_postgresml-0.5.1.dist-info/METADATA
llama_index_indices_managed_postgresml-0.5.1.dist-info/WHEEL
llama_index_indices_managed_postgresml-0.5.1.dist-info/licenses/LICENSE
llama_index_indices_managed_postgresml-0.5.1.dist-info/RECORD
