Metadata-Version: 2.4
Name: llama-index-indices-managed-postgresml
Version: 0.5.1
Summary: llama-index managed postgresml integration
Author-email: PostgresML <team@postgresml.org>
License-Expression: MIT
License-File: LICENSE
Requires-Python: <4.0,>=3.9
Requires-Dist: llama-index-core<0.15,>=0.13.0
Requires-Dist: pgml<2,>=1.1.0
